asfquart/__init__.py
asfquart/auth.py
asfquart/base.py
asfquart/config.py
asfquart/generics.py
asfquart/ldap.py
asfquart/session.py
asfquart/utils.py
asfquart-0.1.11.dist-info/LICENSE
asfquart-0.1.11.dist-info/METADATA
asfquart-0.1.11.dist-info/WHEEL
asfquart-0.1.11.dist-info/RECORD
