Metadata-Version: 2.1
Name: asfquart
Version: 0.1.11
Summary: ASF Quart Framework
Home-page: https://github.com/apache/infrastructure-asfquart
License: Apache-2.0
Author: ASF Infrastructure
Author-email: users@infra.apache.org
Requires-Python: >=3.10,<4
Classifier: Environment :: Web Environment
Classifier: Intended Audience :: Developers
Classifier: License :: OSI Approved :: Apache Software License
Classifier: Operating System :: OS Independent
Classifier: Programming Language :: Python :: 3
Classifier: Programming Language :: Python :: 3.10
Classifier: Programming Language :: Python :: 3.11
Classifier: Programming Language :: Python :: 3.12
Classifier: Programming Language :: Python :: 3.13
Classifier: Topic :: Internet :: WWW/HTTP :: Dynamic Content
Classifier: Topic :: Software Development :: Libraries :: Python Modules
Provides-Extra: aioldap
Requires-Dist: PyYAML (>=6.0.1,<7.0.0)
Requires-Dist: aiohttp (>=3.9.2,<4.0.0)
Requires-Dist: asfpy (>=0.55,<0.56)
Requires-Dist: bonsai ; extra == "aioldap"
Requires-Dist: easydict (>=1.13,<2.0)
Requires-Dist: exceptiongroup (>=1.1.0) ; python_version < "3.11"
Requires-Dist: ezt (>=1.1,<2.0)
Requires-Dist: quart (>=0.20.0,<0.21.0)
Requires-Dist: watchfiles (>=1.0.0,<2.0.0)
Project-URL: Repository, https://github.com/apache/infrastructure-asfquart
